vanty_installer/__init__.py
vanty_installer/__main__.py
vanty_installer-0.0.7.dist-info/entry_points.txt
vanty_installer-0.0.7.dist-info/LICENSE
vanty_installer-0.0.7.dist-info/WHEEL
vanty_installer-0.0.7.dist-info/METADATA
vanty_installer-0.0.7.dist-info/RECORD
