Metadata-Version: 2.1
Name: vanty-installer
Version: 0.0.7
Summary: Installer for the Vanty StarterKit.
Home-page: https://www.advantch.com/
Author: Themba
Author-email: themba@advantch.com
Requires-Python: >=3.7,<4.0
Classifier: Programming Language :: Python :: 3
Classifier: Programming Language :: Python :: 3.7
Classifier: Programming Language :: Python :: 3.8
Classifier: Programming Language :: Python :: 3.9
Requires-Dist: PyYAML (>=5.3.1,<6.0.0)
Requires-Dist: cookiecutter (>=1.7.2,<2.0.0)
Project-URL: Documentation, https://docs.advantch.com
